kobert_transformers/__init__.py
kobert_transformers/load_model.py
kobert_transformers/tokenization_kobert.py
kobert_transformers/utils.py
kobert_transformers/version.txt
kobert_transformers-0.6.0.dist-info/LICENSE
kobert_transformers-0.6.0.dist-info/METADATA
kobert_transformers-0.6.0.dist-info/WHEEL
kobert_transformers-0.6.0.dist-info/top_level.txt
kobert_transformers-0.6.0.dist-info/RECORD
