Metadata-Version: 2.1
Name: kobert-transformers
Version: 0.6.0
Summary: Transformers library for KoBERT, DistilKoBERT
Home-page: https://github.com/monologg/KoBERT-Transformers
Author: Jangwon Park
Author-email: adieujw@gmail.com
License: Apache License 2.0
Keywords: distilkobert kobert bert pytorch transformers lightweight
Requires-Python: >=3.6
License-File: LICENSE
Requires-Dist: torch >=1.1.0
Requires-Dist: transformers <5,>=3
Requires-Dist: sentencepiece >=0.1.91
